README.md
setup.py
mmwebreport/__init__.py
mmwebreport/core/__init__.py
mmwebreport/core/api.py
mmwebreport/core/executor.py
mmwebreport/core/response.py
mmwebreport/main/__init__.py
mmwebreport/main/main.py
mmwebreport/retrieve/__init__.py
mmwebreport/retrieve/cache.py
mmwebreport/retrieve/daterange.py
mmwebreport/retrieve/processing.py
mmwebreport/retrieve/retrieve.py
mmwebreportapi.egg-info/PKG-INFO
mmwebreportapi.egg-info/SOURCES.txt
mmwebreportapi.egg-info/dependency_links.txt
mmwebreportapi.egg-info/entry_points.txt
mmwebreportapi.egg-info/requires.txt
mmwebreportapi.egg-info/top_level.txt