Metadata-Version: 2.1
Name: mmwebreportapi
Version: 0.0.4
Summary: Monitor Manager Web Rerpot API
Home-page: https://github.com/mahulo2009/monitormanager-webreportapi-python.git
Download-URL: https://github.com/mahulo2009/monitormanager-webreportapi-python/archive/refs/tags/v1.0.3-alpha.zip
Author: Manuel Huertas Lopez
Author-email: manuel.huertas.lopez@gmail.com
